dexsuite/__init__.py
dexsuite/api.py
dexsuite/config/__init__.py
dexsuite/config/workspaces.yaml
dexsuite/config/env_configs/arms.yaml
dexsuite/config/env_configs/cameras.yaml
dexsuite/config/env_configs/controllers.yaml
dexsuite/config/env_configs/pose.yaml
dexsuite/config/env_configs/robots.yaml
dexsuite/config/presets/defaults.yaml
dexsuite/config/presets/franka.yaml
dexsuite/controllers/__init__.py
dexsuite/controllers/base_controller.py
dexsuite/controllers/ik_pose.py
dexsuite/controllers/joint_position.py
dexsuite/controllers/joint_torque.py
dexsuite/controllers/joint_velocity.py
dexsuite/controllers/osc_pose.py
dexsuite/controllers/osc_pose_abs.py
dexsuite/controllers/osc_pose_abs_quat.py
dexsuite/core/__init__.py
dexsuite/core/camera.py
dexsuite/core/registry.py
dexsuite/core/components/__init__.py
dexsuite/core/components/arm.py
dexsuite/core/components/base.py
dexsuite/core/components/gripper.py
dexsuite/core/components/mount.py
dexsuite/core/robots/__init__.py
dexsuite/core/robots/bimanual_robot.py
dexsuite/core/robots/factory.py
dexsuite/core/robots/integrated_robot.py
dexsuite/core/robots/modular_robot.py
dexsuite/devices/__init__.py
dexsuite/devices/device.py
dexsuite/devices/external_reset_helper.py
dexsuite/devices/keyboard.py
dexsuite/devices/manus_geort.py
dexsuite/devices/reset_helper.py
dexsuite/devices/spacemouse.py
dexsuite/devices/triad_utils.py
dexsuite/devices/vive_controller.py
dexsuite/devices/vive_tracker.py
dexsuite/environments/__init__.py
dexsuite/environments/base_env.py
dexsuite/environments/bimanual/__init__.py
dexsuite/environments/bimanual/baselines/__init__.py
dexsuite/environments/bimanual/baselines/bimanual_lift.py
dexsuite/environments/bimanual/baselines/bimanual_pick_place.py
dexsuite/environments/bimanual/baselines/bimanual_push.py
dexsuite/environments/bimanual/baselines/bimanual_reach.py
dexsuite/environments/bimanual/baselines/bimanual_stack.py
dexsuite/environments/bimanual/rigid/__init__.py
dexsuite-0.1.4.dist-info/METADATA
dexsuite-0.1.4.dist-info/WHEEL
dexsuite-0.1.4.dist-info/top_level.txt
dexsuite-0.1.4.dist-info/RECORD
