Metadata-Version: 2.1
Name: dexsuite
Version: 0.1.4
Summary: DexSuite: a robotics simulation suite built on Genesis.
License: UNKNOWN
Platform: UNKNOWN
Requires-Python: >=3.10
Requires-Dist: torch
Requires-Dist: genesis-world ==0.3.3
Requires-Dist: pynput
Requires-Dist: pyyaml
Requires-Dist: cattrs
Requires-Dist: gymnasium
Requires-Dist: numpy
Provides-Extra: datasets
Requires-Dist: h5py ; extra == 'datasets'
Provides-Extra: devices
Requires-Dist: openvr ; extra == 'devices'
Requires-Dist: websockets ; extra == 'devices'
Requires-Dist: hidapi ; (platform_system != "Linux") and extra == 'devices'
Requires-Dist: evdev ; (platform_system == "Linux") and extra == 'devices'
Provides-Extra: manus
Requires-Dist: websockets ; extra == 'manus'
Provides-Extra: spacemouse
Requires-Dist: hidapi ; (platform_system != "Linux") and extra == 'spacemouse'
Requires-Dist: evdev ; (platform_system == "Linux") and extra == 'spacemouse'
Provides-Extra: vive
Requires-Dist: openvr ; extra == 'vive'
